appsurifytfs/__init__.py
appsurifytfs/appsurifytfs.py
appsurifytfs-0.0.17.dist-info/LICENCE.txt
appsurifytfs-0.0.17.dist-info/METADATA
appsurifytfs-0.0.17.dist-info/WHEEL
appsurifytfs-0.0.17.dist-info/entry_points.txt
appsurifytfs-0.0.17.dist-info/top_level.txt
appsurifytfs-0.0.17.dist-info/RECORD
